batched_chatgpt/__init__.py
batched_chatgpt/chatgpt_utils.py
batched_chatgpt/utils.py
batched_chatgpt-0.1.1.dist-info/METADATA
batched_chatgpt-0.1.1.dist-info/WHEEL
batched_chatgpt-0.1.1.dist-info/top_level.txt
batched_chatgpt-0.1.1.dist-info/RECORD
