Metadata-Version: 2.1
Name: batched_chatgpt
Version: 0.1.1
Summary: Easy calling chatgpt with batched instances
Author: superheavytail
Author-email: k0s1k0s1k0@korea.ac.kr
Requires-Dist: langchain
Requires-Dist: langchain-openai
Requires-Dist: tqdm
Requires-Dist: openai
